{
  "meta": {
    "experiment": "e1_error_floor",
    "timestamp": "20260522_100612",
    "n_cert_queries": 10,
    "n_noncert_queries": 10,
    "n_train": 5000,
    "n_test": 1000,
    "architectures": [
      "mlp",
      "set_transformer",
      "gnn_og",
      "closure_aware",
      "vanilla_overlap",
      "majority_vote"
    ],
    "seeds": [
      2
    ]
  },
  "results": [
    {
      "model": "mlp",
      "certified": true,
      "seed": 2,
      "test_accuracy": 1.0,
      "test_loss": 3e-06,
      "n_epochs": 53,
      "stopped_early": true,
      "train_time_s": 4.999,
      "query_type": "certified"
    },
    {
      "model": "set_transformer",
      "certified": true,
      "seed": 2,
      "test_accuracy": 1.0,
      "test_loss": 1e-06,
      "n_epochs": 43,
      "stopped_early": true,
      "train_time_s": 4.188,
      "query_type": "certified"
    },
    {
      "model": "gnn_og",
      "certified": true,
      "seed": 2,
      "test_accuracy": 1.0,
      "test_loss": 0.0,
      "n_epochs": 32,
      "stopped_early": true,
      "train_time_s": 2.778,
      "query_type": "certified"
    },
    {
      "model": "closure_aware",
      "certified": true,
      "seed": 2,
      "test_accuracy": 1.0,
      "test_loss": 0.0,
      "n_epochs": 32,
      "stopped_early": true,
      "train_time_s": 2.734,
      "query_type": "certified"
    },
    {
      "model": "vanilla_overlap",
      "certified": true,
      "seed": 2,
      "test_accuracy": 1.0,
      "test_loss": 0.00834,
      "n_epochs": 300,
      "stopped_early": false,
      "train_time_s": 10.592,
      "query_type": "certified"
    },
    {
      "model": "majority_vote",
      "certified": true,
      "seed": 2,
      "test_accuracy": 1.0,
      "test_loss": 0.02629,
      "n_epochs": 300,
      "stopped_early": false,
      "train_time_s": 9.987,
      "query_type": "certified"
    },
    {
      "model": "mlp",
      "certified": true,
      "seed": 2,
      "test_accuracy": 1.0,
      "test_loss": 3e-05,
      "n_epochs": 276,
      "stopped_early": true,
      "train_time_s": 11.589,
      "query_type": "certified"
    },
    {
      "model": "set_transformer",
      "certified": true,
      "seed": 2,
      "test_accuracy": 1.0,
      "test_loss": 2e-06,
      "n_epochs": 50,
      "stopped_early": true,
      "train_time_s": 4.713,
      "query_type": "certified"
    },
    {
      "model": "gnn_og",
      "certified": true,
      "seed": 2,
      "test_accuracy": 1.0,
      "test_loss": 1e-05,
      "n_epochs": 126,
      "stopped_early": true,
      "train_time_s": 10.968,
      "query_type": "certified"
    },
    {
      "model": "closure_aware",
      "certified": true,
      "seed": 2,
      "test_accuracy": 0.999,
      "test_loss": 0.016417,
      "n_epochs": 32,
      "stopped_early": true,
      "train_time_s": 2.801,
      "query_type": "certified"
    },
    {
      "model": "vanilla_overlap",
      "certified": true,
      "seed": 2,
      "test_accuracy": 0.997,
      "test_loss": 0.021071,
      "n_epochs": 300,
      "stopped_early": false,
      "train_time_s": 10.417,
      "query_type": "certified"
    },
    {
      "model": "majority_vote",
      "certified": true,
      "seed": 2,
      "test_accuracy": 1.0,
      "test_loss": 0.02651,
      "n_epochs": 300,
      "stopped_early": false,
      "train_time_s": 9.764,
      "query_type": "certified"
    },
    {
      "model": "mlp",
      "certified": true,
      "seed": 2,
      "test_accuracy": 1.0,
      "test_loss": 3e-06,
      "n_epochs": 49,
      "stopped_early": true,
      "train_time_s": 2.009,
      "query_type": "certified"
    },
    {
      "model": "set_transformer",
      "certified": true,
      "seed": 2,
      "test_accuracy": 1.0,
      "test_loss": 1e-06,
      "n_epochs": 43,
      "stopped_early": true,
      "train_time_s": 4.022,
      "query_type": "certified"
    },
    {
      "model": "gnn_og",
      "certified": true,
      "seed": 2,
      "test_accuracy": 1.0,
      "test_loss": 0.0,
      "n_epochs": 32,
      "stopped_early": true,
      "train_time_s": 2.735,
      "query_type": "certified"
    },
    {
      "model": "closure_aware",
      "certified": true,
      "seed": 2,
      "test_accuracy": 1.0,
      "test_loss": 0.0,
      "n_epochs": 32,
      "stopped_early": true,
      "train_time_s": 2.799,
      "query_type": "certified"
    },
    {
      "model": "vanilla_overlap",
      "certified": true,
      "seed": 2,
      "test_accuracy": 1.0,
      "test_loss": 0.008346,
      "n_epochs": 300,
      "stopped_early": false,
      "train_time_s": 10.389,
      "query_type": "certified"
    },
    {
      "model": "majority_vote",
      "certified": true,
      "seed": 2,
      "test_accuracy": 1.0,
      "test_loss": 0.02629,
      "n_epochs": 300,
      "stopped_early": false,
      "train_time_s": 9.829,
      "query_type": "certified"
    },
    {
      "model": "mlp",
      "certified": true,
      "seed": 2,
      "test_accuracy": 1.0,
      "test_loss": 0.000147,
      "n_epochs": 216,
      "stopped_early": true,
      "train_time_s": 8.879,
      "query_type": "certified"
    },
    {
      "model": "set_transformer",
      "certified": true,
      "seed": 2,
      "test_accuracy": 1.0,
      "test_loss": 0.0,
      "n_epochs": 118,
      "stopped_early": true,
      "train_time_s": 11.405,
      "query_type": "certified"
    },
    {
      "model": "gnn_og",
      "certified": true,
      "seed": 2,
      "test_accuracy": 1.0,
      "test_loss": 1.1e-05,
      "n_epochs": 117,
      "stopped_early": true,
      "train_time_s": 10.076,
      "query_type": "certified"
    },
    {
      "model": "closure_aware",
      "certified": true,
      "seed": 2,
      "test_accuracy": 1.0,
      "test_loss": 1.1e-05,
      "n_epochs": 174,
      "stopped_early": true,
      "train_time_s": 14.678,
      "query_type": "certified"
    },
    {
      "model": "vanilla_overlap",
      "certified": true,
      "seed": 2,
      "test_accuracy": 0.999,
      "test_loss": 0.011218,
      "n_epochs": 300,
      "stopped_early": false,
      "train_time_s": 10.656,
      "query_type": "certified"
    },
    {
      "model": "majority_vote",
      "certified": true,
      "seed": 2,
      "test_accuracy": 1.0,
      "test_loss": 0.026815,
      "n_epochs": 300,
      "stopped_early": false,
      "train_time_s": 9.774,
      "query_type": "certified"
    },
    {
      "model": "mlp",
      "certified": true,
      "seed": 2,
      "test_accuracy": 1.0,
      "test_loss": 3e-06,
      "n_epochs": 49,
      "stopped_early": true,
      "train_time_s": 2.055,
      "query_type": "certified"
    },
    {
      "model": "set_transformer",
      "certified": true,
      "seed": 2,
      "test_accuracy": 1.0,
      "test_loss": 1e-06,
      "n_epochs": 43,
      "stopped_early": true,
      "train_time_s": 4.175,
      "query_type": "certified"
    },
    {
      "model": "gnn_og",
      "certified": true,
      "seed": 2,
      "test_accuracy": 1.0,
      "test_loss": 0.0,
      "n_epochs": 32,
      "stopped_early": true,
      "train_time_s": 2.748,
      "query_type": "certified"
    },
    {
      "model": "closure_aware",
      "certified": true,
      "seed": 2,
      "test_accuracy": 1.0,
      "test_loss": 0.0,
      "n_epochs": 32,
      "stopped_early": true,
      "train_time_s": 2.793,
      "query_type": "certified"
    },
    {
      "model": "vanilla_overlap",
      "certified": true,
      "seed": 2,
      "test_accuracy": 1.0,
      "test_loss": 0.008336,
      "n_epochs": 300,
      "stopped_early": false,
      "train_time_s": 10.465,
      "query_type": "certified"
    },
    {
      "model": "majority_vote",
      "certified": true,
      "seed": 2,
      "test_accuracy": 1.0,
      "test_loss": 0.02629,
      "n_epochs": 300,
      "stopped_early": false,
      "train_time_s": 9.771,
      "query_type": "certified"
    },
    {
      "model": "mlp",
      "certified": true,
      "seed": 2,
      "test_accuracy": 1.0,
      "test_loss": 1.4e-05,
      "n_epochs": 218,
      "stopped_early": true,
      "train_time_s": 8.952,
      "query_type": "certified"
    },
    {
      "model": "set_transformer",
      "certified": true,
      "seed": 2,
      "test_accuracy": 1.0,
      "test_loss": 2e-06,
      "n_epochs": 45,
      "stopped_early": true,
      "train_time_s": 4.357,
      "query_type": "certified"
    },
    {
      "model": "gnn_og",
      "certified": true,
      "seed": 2,
      "test_accuracy": 1.0,
      "test_loss": 3e-06,
      "n_epochs": 84,
      "stopped_early": true,
      "train_time_s": 7.298,
      "query_type": "certified"
    },
    {
      "model": "closure_aware",
      "certified": true,
      "seed": 2,
      "test_accuracy": 1.0,
      "test_loss": 2e-06,
      "n_epochs": 100,
      "stopped_early": true,
      "train_time_s": 8.665,
      "query_type": "certified"
    },
    {
      "model": "vanilla_overlap",
      "certified": true,
      "seed": 2,
      "test_accuracy": 0.999,
      "test_loss": 0.011422,
      "n_epochs": 300,
      "stopped_early": false,
      "train_time_s": 10.672,
      "query_type": "certified"
    },
    {
      "model": "majority_vote",
      "certified": true,
      "seed": 2,
      "test_accuracy": 0.996,
      "test_loss": 0.040979,
      "n_epochs": 300,
      "stopped_early": false,
      "train_time_s": 10.058,
      "query_type": "certified"
    },
    {
      "model": "mlp",
      "certified": true,
      "seed": 2,
      "test_accuracy": 1.0,
      "test_loss": 3e-06,
      "n_epochs": 53,
      "stopped_early": true,
      "train_time_s": 2.255,
      "query_type": "certified"
    },
    {
      "model": "set_transformer",
      "certified": true,
      "seed": 2,
      "test_accuracy": 1.0,
      "test_loss": 1e-06,
      "n_epochs": 43,
      "stopped_early": true,
      "train_time_s": 4.171,
      "query_type": "certified"
    },
    {
      "model": "gnn_og",
      "certified": true,
      "seed": 2,
      "test_accuracy": 1.0,
      "test_loss": 0.0,
      "n_epochs": 32,
      "stopped_early": true,
      "train_time_s": 2.748,
      "query_type": "certified"
    },
    {
      "model": "closure_aware",
      "certified": true,
      "seed": 2,
      "test_accuracy": 1.0,
      "test_loss": 0.0,
      "n_epochs": 32,
      "stopped_early": true,
      "train_time_s": 2.797,
      "query_type": "certified"
    },
    {
      "model": "vanilla_overlap",
      "certified": true,
      "seed": 2,
      "test_accuracy": 1.0,
      "test_loss": 0.008331,
      "n_epochs": 300,
      "stopped_early": false,
      "train_time_s": 10.49,
      "query_type": "certified"
    },
    {
      "model": "majority_vote",
      "certified": true,
      "seed": 2,
      "test_accuracy": 1.0,
      "test_loss": 0.02629,
      "n_epochs": 300,
      "stopped_early": false,
      "train_time_s": 10.008,
      "query_type": "certified"
    },
    {
      "model": "mlp",
      "certified": true,
      "seed": 2,
      "test_accuracy": 1.0,
      "test_loss": 3e-06,
      "n_epochs": 49,
      "stopped_early": true,
      "train_time_s": 2.042,
      "query_type": "certified"
    },
    {
      "model": "set_transformer",
      "certified": true,
      "seed": 2,
      "test_accuracy": 1.0,
      "test_loss": 1e-06,
      "n_epochs": 43,
      "stopped_early": true,
      "train_time_s": 4.169,
      "query_type": "certified"
    },
    {
      "model": "gnn_og",
      "certified": true,
      "seed": 2,
      "test_accuracy": 1.0,
      "test_loss": 0.0,
      "n_epochs": 32,
      "stopped_early": true,
      "train_time_s": 2.782,
      "query_type": "certified"
    },
    {
      "model": "closure_aware",
      "certified": true,
      "seed": 2,
      "test_accuracy": 1.0,
      "test_loss": 0.0,
      "n_epochs": 32,
      "stopped_early": true,
      "train_time_s": 2.782,
      "query_type": "certified"
    },
    {
      "model": "vanilla_overlap",
      "certified": true,
      "seed": 2,
      "test_accuracy": 1.0,
      "test_loss": 0.00834,
      "n_epochs": 300,
      "stopped_early": false,
      "train_time_s": 10.415,
      "query_type": "certified"
    },
    {
      "model": "majority_vote",
      "certified": true,
      "seed": 2,
      "test_accuracy": 1.0,
      "test_loss": 0.02629,
      "n_epochs": 300,
      "stopped_early": false,
      "train_time_s": 9.788,
      "query_type": "certified"
    },
    {
      "model": "mlp",
      "certified": true,
      "seed": 2,
      "test_accuracy": 1.0,
      "test_loss": 3e-06,
      "n_epochs": 51,
      "stopped_early": true,
      "train_time_s": 2.088,
      "query_type": "certified"
    },
    {
      "model": "set_transformer",
      "certified": true,
      "seed": 2,
      "test_accuracy": 1.0,
      "test_loss": 1e-06,
      "n_epochs": 43,
      "stopped_early": true,
      "train_time_s": 4.205,
      "query_type": "certified"
    },
    {
      "model": "gnn_og",
      "certified": true,
      "seed": 2,
      "test_accuracy": 1.0,
      "test_loss": 0.0,
      "n_epochs": 32,
      "stopped_early": true,
      "train_time_s": 2.73,
      "query_type": "certified"
    },
    {
      "model": "closure_aware",
      "certified": true,
      "seed": 2,
      "test_accuracy": 1.0,
      "test_loss": 0.0,
      "n_epochs": 32,
      "stopped_early": true,
      "train_time_s": 2.787,
      "query_type": "certified"
    },
    {
      "model": "vanilla_overlap",
      "certified": true,
      "seed": 2,
      "test_accuracy": 1.0,
      "test_loss": 0.008338,
      "n_epochs": 300,
      "stopped_early": false,
      "train_time_s": 10.439,
      "query_type": "certified"
    },
    {
      "model": "majority_vote",
      "certified": true,
      "seed": 2,
      "test_accuracy": 1.0,
      "test_loss": 0.02629,
      "n_epochs": 300,
      "stopped_early": false,
      "train_time_s": 9.844,
      "query_type": "certified"
    },
    {
      "model": "mlp",
      "certified": true,
      "seed": 2,
      "test_accuracy": 1.0,
      "test_loss": 3e-06,
      "n_epochs": 48,
      "stopped_early": true,
      "train_time_s": 1.972,
      "query_type": "certified"
    },
    {
      "model": "set_transformer",
      "certified": true,
      "seed": 2,
      "test_accuracy": 1.0,
      "test_loss": 1e-06,
      "n_epochs": 43,
      "stopped_early": true,
      "train_time_s": 4.13,
      "query_type": "certified"
    },
    {
      "model": "gnn_og",
      "certified": true,
      "seed": 2,
      "test_accuracy": 1.0,
      "test_loss": 0.0,
      "n_epochs": 32,
      "stopped_early": true,
      "train_time_s": 2.776,
      "query_type": "certified"
    },
    {
      "model": "closure_aware",
      "certified": true,
      "seed": 2,
      "test_accuracy": 1.0,
      "test_loss": 0.0,
      "n_epochs": 32,
      "stopped_early": true,
      "train_time_s": 2.734,
      "query_type": "certified"
    },
    {
      "model": "vanilla_overlap",
      "certified": true,
      "seed": 2,
      "test_accuracy": 1.0,
      "test_loss": 0.008331,
      "n_epochs": 300,
      "stopped_early": false,
      "train_time_s": 10.48,
      "query_type": "certified"
    },
    {
      "model": "majority_vote",
      "certified": true,
      "seed": 2,
      "test_accuracy": 1.0,
      "test_loss": 0.02629,
      "n_epochs": 300,
      "stopped_early": false,
      "train_time_s": 9.789,
      "query_type": "certified"
    },
    {
      "model": "mlp",
      "certified": false,
      "seed": 2,
      "test_accuracy": 0.944,
      "test_loss": 0.18726,
      "n_epochs": 87,
      "stopped_early": true,
      "train_time_s": 3.576,
      "query_type": "noncertified"
    },
    {
      "model": "set_transformer",
      "certified": false,
      "seed": 2,
      "test_accuracy": 0.954,
      "test_loss": 0.172199,
      "n_epochs": 59,
      "stopped_early": true,
      "train_time_s": 5.61,
      "query_type": "noncertified"
    },
    {
      "model": "gnn_og",
      "certified": false,
      "seed": 2,
      "test_accuracy": 0.941,
      "test_loss": 0.182742,
      "n_epochs": 242,
      "stopped_early": true,
      "train_time_s": 20.92,
      "query_type": "noncertified"
    },
    {
      "model": "closure_aware",
      "certified": false,
      "seed": 2,
      "test_accuracy": 0.058,
      "test_loss": 0.693147,
      "n_epochs": 0,
      "stopped_early": false,
      "train_time_s": 0.0,
      "query_type": "noncertified"
    },
    {
      "model": "vanilla_overlap",
      "certified": false,
      "seed": 2,
      "test_accuracy": 0.953,
      "test_loss": 0.168186,
      "n_epochs": 300,
      "stopped_early": false,
      "train_time_s": 10.411,
      "query_type": "noncertified"
    },
    {
      "model": "majority_vote",
      "certified": false,
      "seed": 2,
      "test_accuracy": 0.92,
      "test_loss": 0.281846,
      "n_epochs": 300,
      "stopped_early": false,
      "train_time_s": 9.804,
      "query_type": "noncertified"
    },
    {
      "model": "mlp",
      "certified": false,
      "seed": 2,
      "test_accuracy": 0.937,
      "test_loss": 0.200223,
      "n_epochs": 51,
      "stopped_early": true,
      "train_time_s": 2.088,
      "query_type": "noncertified"
    },
    {
      "model": "set_transformer",
      "certified": false,
      "seed": 2,
      "test_accuracy": 0.932,
      "test_loss": 0.20504,
      "n_epochs": 78,
      "stopped_early": true,
      "train_time_s": 7.593,
      "query_type": "noncertified"
    },
    {
      "model": "gnn_og",
      "certified": false,
      "seed": 2,
      "test_accuracy": 0.937,
      "test_loss": 0.204878,
      "n_epochs": 54,
      "stopped_early": true,
      "train_time_s": 4.707,
      "query_type": "noncertified"
    },
    {
      "model": "closure_aware",
      "certified": false,
      "seed": 2,
      "test_accuracy": 0.052,
      "test_loss": 0.693147,
      "n_epochs": 0,
      "stopped_early": false,
      "train_time_s": 0.0,
      "query_type": "noncertified"
    },
    {
      "model": "vanilla_overlap",
      "certified": false,
      "seed": 2,
      "test_accuracy": 0.948,
      "test_loss": 0.18614,
      "n_epochs": 300,
      "stopped_early": false,
      "train_time_s": 10.453,
      "query_type": "noncertified"
    },
    {
      "model": "majority_vote",
      "certified": false,
      "seed": 2,
      "test_accuracy": 0.951,
      "test_loss": 0.196105,
      "n_epochs": 300,
      "stopped_early": false,
      "train_time_s": 9.796,
      "query_type": "noncertified"
    },
    {
      "model": "mlp",
      "certified": false,
      "seed": 2,
      "test_accuracy": 0.95,
      "test_loss": 0.169375,
      "n_epochs": 128,
      "stopped_early": true,
      "train_time_s": 5.254,
      "query_type": "noncertified"
    },
    {
      "model": "set_transformer",
      "certified": false,
      "seed": 2,
      "test_accuracy": 0.96,
      "test_loss": 0.141767,
      "n_epochs": 32,
      "stopped_early": true,
      "train_time_s": 3.102,
      "query_type": "noncertified"
    },
    {
      "model": "gnn_og",
      "certified": false,
      "seed": 2,
      "test_accuracy": 0.958,
      "test_loss": 0.153332,
      "n_epochs": 101,
      "stopped_early": true,
      "train_time_s": 8.766,
      "query_type": "noncertified"
    },
    {
      "model": "closure_aware",
      "certified": false,
      "seed": 2,
      "test_accuracy": 0.056,
      "test_loss": 0.693147,
      "n_epochs": 0,
      "stopped_early": false,
      "train_time_s": 0.0,
      "query_type": "noncertified"
    },
    {
      "model": "vanilla_overlap",
      "certified": false,
      "seed": 2,
      "test_accuracy": 0.954,
      "test_loss": 0.170247,
      "n_epochs": 300,
      "stopped_early": false,
      "train_time_s": 10.437,
      "query_type": "noncertified"
    },
    {
      "model": "majority_vote",
      "certified": false,
      "seed": 2,
      "test_accuracy": 0.952,
      "test_loss": 0.193286,
      "n_epochs": 300,
      "stopped_early": false,
      "train_time_s": 9.797,
      "query_type": "noncertified"
    },
    {
      "model": "mlp",
      "certified": false,
      "seed": 2,
      "test_accuracy": 0.946,
      "test_loss": 0.180694,
      "n_epochs": 37,
      "stopped_early": true,
      "train_time_s": 1.528,
      "query_type": "noncertified"
    },
    {
      "model": "set_transformer",
      "certified": false,
      "seed": 2,
      "test_accuracy": 0.935,
      "test_loss": 0.207326,
      "n_epochs": 52,
      "stopped_early": true,
      "train_time_s": 5.008,
      "query_type": "noncertified"
    },
    {
      "model": "gnn_og",
      "certified": false,
      "seed": 2,
      "test_accuracy": 0.957,
      "test_loss": 0.155292,
      "n_epochs": 136,
      "stopped_early": true,
      "train_time_s": 11.79,
      "query_type": "noncertified"
    },
    {
      "model": "closure_aware",
      "certified": false,
      "seed": 2,
      "test_accuracy": 0.065,
      "test_loss": 0.693147,
      "n_epochs": 0,
      "stopped_early": false,
      "train_time_s": 0.0,
      "query_type": "noncertified"
    },
    {
      "model": "vanilla_overlap",
      "certified": false,
      "seed": 2,
      "test_accuracy": 0.934,
      "test_loss": 0.217614,
      "n_epochs": 300,
      "stopped_early": false,
      "train_time_s": 10.54,
      "query_type": "noncertified"
    },
    {
      "model": "majority_vote",
      "certified": false,
      "seed": 2,
      "test_accuracy": 0.944,
      "test_loss": 0.216072,
      "n_epochs": 300,
      "stopped_early": false,
      "train_time_s": 9.998,
      "query_type": "noncertified"
    },
    {
      "model": "mlp",
      "certified": false,
      "seed": 2,
      "test_accuracy": 0.946,
      "test_loss": 0.170857,
      "n_epochs": 110,
      "stopped_early": true,
      "train_time_s": 4.579,
      "query_type": "noncertified"
    },
    {
      "model": "set_transformer",
      "certified": false,
      "seed": 2,
      "test_accuracy": 0.956,
      "test_loss": 0.146749,
      "n_epochs": 49,
      "stopped_early": true,
      "train_time_s": 4.706,
      "query_type": "noncertified"
    },
    {
      "model": "gnn_og",
      "certified": false,
      "seed": 2,
      "test_accuracy": 0.938,
      "test_loss": 0.189738,
      "n_epochs": 67,
      "stopped_early": true,
      "train_time_s": 5.812,
      "query_type": "noncertified"
    },
    {
      "model": "closure_aware",
      "certified": false,
      "seed": 2,
      "test_accuracy": 0.063,
      "test_loss": 0.693147,
      "n_epochs": 0,
      "stopped_early": false,
      "train_time_s": 0.0,
      "query_type": "noncertified"
    },
    {
      "model": "vanilla_overlap",
      "certified": false,
      "seed": 2,
      "test_accuracy": 0.949,
      "test_loss": 0.183972,
      "n_epochs": 300,
      "stopped_early": false,
      "train_time_s": 10.429,
      "query_type": "noncertified"
    },
    {
      "model": "majority_vote",
      "certified": false,
      "seed": 2,
      "test_accuracy": 0.953,
      "test_loss": 0.190444,
      "n_epochs": 300,
      "stopped_early": false,
      "train_time_s": 9.797,
      "query_type": "noncertified"
    },
    {
      "model": "mlp",
      "certified": false,
      "seed": 2,
      "test_accuracy": 0.949,
      "test_loss": 0.170496,
      "n_epochs": 82,
      "stopped_early": true,
      "train_time_s": 3.379,
      "query_type": "noncertified"
    },
    {
      "model": "set_transformer",
      "certified": false,
      "seed": 2,
      "test_accuracy": 0.95,
      "test_loss": 0.171622,
      "n_epochs": 44,
      "stopped_early": true,
      "train_time_s": 4.231,
      "query_type": "noncertified"
    },
    {
      "model": "gnn_og",
      "certified": false,
      "seed": 2,
      "test_accuracy": 0.957,
      "test_loss": 0.153752,
      "n_epochs": 145,
      "stopped_early": true,
      "train_time_s": 12.547,
      "query_type": "noncertified"
    },
    {
      "model": "closure_aware",
      "certified": false,
      "seed": 2,
      "test_accuracy": 0.046,
      "test_loss": 0.693147,
      "n_epochs": 0,
      "stopped_early": false,
      "train_time_s": 0.0,
      "query_type": "noncertified"
    },
    {
      "model": "vanilla_overlap",
      "certified": false,
      "seed": 2,
      "test_accuracy": 0.937,
      "test_loss": 0.214829,
      "n_epochs": 300,
      "stopped_early": false,
      "train_time_s": 10.439,
      "query_type": "noncertified"
    },
    {
      "model": "majority_vote",
      "certified": false,
      "seed": 2,
      "test_accuracy": 0.942,
      "test_loss": 0.221569,
      "n_epochs": 300,
      "stopped_early": false,
      "train_time_s": 9.859,
      "query_type": "noncertified"
    },
    {
      "model": "mlp",
      "certified": false,
      "seed": 2,
      "test_accuracy": 0.938,
      "test_loss": 0.203218,
      "n_epochs": 90,
      "stopped_early": true,
      "train_time_s": 3.691,
      "query_type": "noncertified"
    },
    {
      "model": "set_transformer",
      "certified": false,
      "seed": 2,
      "test_accuracy": 0.955,
      "test_loss": 0.159686,
      "n_epochs": 64,
      "stopped_early": true,
      "train_time_s": 6.129,
      "query_type": "noncertified"
    },
    {
      "model": "gnn_og",
      "certified": false,
      "seed": 2,
      "test_accuracy": 0.944,
      "test_loss": 0.184092,
      "n_epochs": 154,
      "stopped_early": true,
      "train_time_s": 13.354,
      "query_type": "noncertified"
    },
    {
      "model": "closure_aware",
      "certified": false,
      "seed": 2,
      "test_accuracy": 0.054,
      "test_loss": 0.693147,
      "n_epochs": 0,
      "stopped_early": false,
      "train_time_s": 0.0,
      "query_type": "noncertified"
    },
    {
      "model": "vanilla_overlap",
      "certified": false,
      "seed": 2,
      "test_accuracy": 0.944,
      "test_loss": 0.194994,
      "n_epochs": 300,
      "stopped_early": false,
      "train_time_s": 10.457,
      "query_type": "noncertified"
    },
    {
      "model": "majority_vote",
      "certified": false,
      "seed": 2,
      "test_accuracy": 0.948,
      "test_loss": 0.205485,
      "n_epochs": 300,
      "stopped_early": false,
      "train_time_s": 9.863,
      "query_type": "noncertified"
    },
    {
      "model": "mlp",
      "certified": false,
      "seed": 2,
      "test_accuracy": 0.936,
      "test_loss": 0.202331,
      "n_epochs": 37,
      "stopped_early": true,
      "train_time_s": 1.527,
      "query_type": "noncertified"
    },
    {
      "model": "set_transformer",
      "certified": false,
      "seed": 2,
      "test_accuracy": 0.946,
      "test_loss": 0.184319,
      "n_epochs": 89,
      "stopped_early": true,
      "train_time_s": 8.227,
      "query_type": "noncertified"
    },
    {
      "model": "gnn_og",
      "certified": false,
      "seed": 2,
      "test_accuracy": 0.957,
      "test_loss": 0.155225,
      "n_epochs": 43,
      "stopped_early": true,
      "train_time_s": 3.624,
      "query_type": "noncertified"
    },
    {
      "model": "closure_aware",
      "certified": false,
      "seed": 2,
      "test_accuracy": 0.051,
      "test_loss": 0.693147,
      "n_epochs": 0,
      "stopped_early": false,
      "train_time_s": 0.0,
      "query_type": "noncertified"
    },
    {
      "model": "vanilla_overlap",
      "certified": false,
      "seed": 2,
      "test_accuracy": 0.942,
      "test_loss": 0.202783,
      "n_epochs": 300,
      "stopped_early": false,
      "train_time_s": 10.603,
      "query_type": "noncertified"
    },
    {
      "model": "majority_vote",
      "certified": false,
      "seed": 2,
      "test_accuracy": 0.951,
      "test_loss": 0.196686,
      "n_epochs": 300,
      "stopped_early": false,
      "train_time_s": 9.77,
      "query_type": "noncertified"
    },
    {
      "model": "mlp",
      "certified": false,
      "seed": 2,
      "test_accuracy": 0.946,
      "test_loss": 0.166261,
      "n_epochs": 64,
      "stopped_early": true,
      "train_time_s": 2.666,
      "query_type": "noncertified"
    },
    {
      "model": "set_transformer",
      "certified": false,
      "seed": 2,
      "test_accuracy": 0.947,
      "test_loss": 0.169885,
      "n_epochs": 57,
      "stopped_early": true,
      "train_time_s": 5.433,
      "query_type": "noncertified"
    },
    {
      "model": "gnn_og",
      "certified": false,
      "seed": 2,
      "test_accuracy": 0.944,
      "test_loss": 0.171245,
      "n_epochs": 62,
      "stopped_early": true,
      "train_time_s": 5.392,
      "query_type": "noncertified"
    },
    {
      "model": "closure_aware",
      "certified": false,
      "seed": 2,
      "test_accuracy": 0.053,
      "test_loss": 0.693147,
      "n_epochs": 0,
      "stopped_early": false,
      "train_time_s": 0.0,
      "query_type": "noncertified"
    },
    {
      "model": "vanilla_overlap",
      "certified": false,
      "seed": 2,
      "test_accuracy": 0.94,
      "test_loss": 0.205776,
      "n_epochs": 300,
      "stopped_early": false,
      "train_time_s": 10.443,
      "query_type": "noncertified"
    },
    {
      "model": "majority_vote",
      "certified": false,
      "seed": 2,
      "test_accuracy": 0.935,
      "test_loss": 0.24093,
      "n_epochs": 300,
      "stopped_early": false,
      "train_time_s": 9.804,
      "query_type": "noncertified"
    },
    {
      "model": "mlp",
      "certified": false,
      "seed": 2,
      "test_accuracy": 0.949,
      "test_loss": 0.174504,
      "n_epochs": 50,
      "stopped_early": true,
      "train_time_s": 2.098,
      "query_type": "noncertified"
    },
    {
      "model": "set_transformer",
      "certified": false,
      "seed": 2,
      "test_accuracy": 0.943,
      "test_loss": 0.193636,
      "n_epochs": 71,
      "stopped_early": true,
      "train_time_s": 6.714,
      "query_type": "noncertified"
    },
    {
      "model": "gnn_og",
      "certified": false,
      "seed": 2,
      "test_accuracy": 0.942,
      "test_loss": 0.188348,
      "n_epochs": 34,
      "stopped_early": true,
      "train_time_s": 2.953,
      "query_type": "noncertified"
    },
    {
      "model": "closure_aware",
      "certified": false,
      "seed": 2,
      "test_accuracy": 0.066,
      "test_loss": 0.693147,
      "n_epochs": 0,
      "stopped_early": false,
      "train_time_s": 0.0,
      "query_type": "noncertified"
    },
    {
      "model": "vanilla_overlap",
      "certified": false,
      "seed": 2,
      "test_accuracy": 0.947,
      "test_loss": 0.194067,
      "n_epochs": 300,
      "stopped_early": false,
      "train_time_s": 10.522,
      "query_type": "noncertified"
    },
    {
      "model": "majority_vote",
      "certified": false,
      "seed": 2,
      "test_accuracy": 0.951,
      "test_loss": 0.196995,
      "n_epochs": 300,
      "stopped_early": false,
      "train_time_s": 9.959,
      "query_type": "noncertified"
    }
  ]
}